word_prediction_kb_bert/__init__.py
word_prediction_kb_bert/predictor.py
sparv_word_prediction_kb_bert_plugin-0.5.2.dist-info/METADATA
sparv_word_prediction_kb_bert_plugin-0.5.2.dist-info/WHEEL
sparv_word_prediction_kb_bert_plugin-0.5.2.dist-info/entry_points.txt
sparv_word_prediction_kb_bert_plugin-0.5.2.dist-info/RECORD
