Metadata-Version: 2.3
Name: sparv-word-prediction-kb-bert-plugin
Version: 0.5.2
Summary: A sparv plugin for computing word neighbours using a BERT model.
Project-URL: Homepage, https://spraakbanken.gu.se
Project-URL: Repository, https://github.com/spraakbanken/sparv-word-prediction-plugin
Project-URL: Bug Tracker, https://github.com/spraakbanken/sparv-word-prediction-plugin/labels/project%3Aword-prediction--kb-bert
Author-email: Kristoffer Andersson <kristoffer.andersson@gu.se>
License-Expression: MIT
Classifier: Development Status :: 4 - Beta
Classifier: Intended Audience :: Developers
Classifier: License :: OSI Approved :: MIT License
Classifier: Operating System :: POSIX
Classifier: Operating System :: Unix
Classifier: Programming Language :: Python :: Implementation :: CPython
Classifier: Topic :: Utilities
Requires-Python: >=3.9
Requires-Dist: sparv-pipeline>=5.2.0
Requires-Dist: tabulate>=0.9.0
Requires-Dist: transformers>=4.34.1
